comparator_1_bit.v
module comparator_1_bit(A,B,Eq,G,L);
    input A,B;
    output Eq,G,L;

    xnor G1 (Eq,A,B);
    and G2 (G,A,~B),
        G3 (L,~A,B);

endmodule

half_adder.v
module half_adder(A,B,Sum,C_out);
    input A,B;
    output C_out,Sum;

    xor  G1  (Sum,A,B)   ;
    and G2  (C_out,A,B) ; 

endmodule

full_adder.v
`include "half_adder.v"

module full_adder(A,B,C_in,Sum,C_out);
    input   A,B,C_in    ;
    output  Sum,C_out   ;

    wire t1,t2,t3   ;

    half_adder  H1(A,B,t1,t2)       ;
    half_adder  H2(t1,C_in,Sum,t3)  ;

    xor G1(C_out,t2,t3)  ;

endmodule

decoder_2to4.v
module decoder_2to4 (S0,S1,R0,R1,R2,R3);

    input   S0, S1;
    output  R0,R1,R2,R3;

    wire inv0,inv1;

    not G1 (inv0,S0),
        G2 (inv1,S1);

    and G3 (R0,inv0,inv1),
        G4 (R1,S0,inv1),
        G5 (R2,inv0,S1),
        G6 (R3,S0,S1);

endmodule

ALU_1_bit.v
module ALU_1_bit(A,B,Cin,M0,M1,F,Cout,N);
    input A,B,Cin,M0,M1 ;
    output F, Cout,N;
    // When performing arithmetic operations F, Cout and N are used to represent the result, the carry out and negative
    // when ALU is in comparator mode, F --> A == B, Cout --> A>B, N --> A<B

    wire t0,t1,t2,t3;
    decoder_2to4 dcd1(M0,M1,t0,t1,t2,t3);

    wire [2:0]EN_add,EN_sub;
    wire [1:0]EN_cmp,EN_and;

    and (EN_add[0],t0,A),
        (EN_add[1],t0,B),
        (EN_add[2],t0,Cin),
        (EN_sub[0],t1,A),
        (EN_sub[1],t1,B^t1),
        (EN_sub[2],t1,Cin^t1),
        (EN_cmp[0],t2,A),
        (EN_cmp[1],t2,B),
        (EN_and[0],t3,A),
        (EN_and[1],t3,B);

    wire j0,j1,j2,F0,F1,F2,C0,C1;

    or  (j0,EN_add[0],EN_sub[0]),
        (j1,EN_add[1],EN_sub[1]),
        (j2,EN_add[2],EN_sub[2]);
        
    full_adder f1(j0,j1,j2,F0,C0);
    comparator_1_bit cmp1(EN_cmp[0],EN_cmp[1],F1,C1,N);
    and (F2,EN_and[0],EN_and[1]);

    or (F,F0&(t0|t1),F1&t2,F2&t3);
    or (Cout,C0&(t0|t1),C1&t2);
    

endmodule

tb_ALU_1_bit.v
`include "half_adder.v"
`include "full_adder.v"
`include "comparator_1_bit.v"
`include "decoder_2to4.v"
`include "ALU_1_bit.v"

module tb_ALU_1b;
    reg A,B,Cin,M0,M1;
    wire F, Cout, N;

    ALU_1_bit DUT(A,B,Cin,M0,M1,F,Cout,N);

    initial 
        begin
            $dumpfile("tb_ALU_1b.vcd");
            $dumpvars(0,tb_ALU_1b);
            
            $monitor($time," M1 = %b, M0 = %b, A = %b, B = %b, Cin = %b, F = %b, Cout = %b, N = %b",M1,M0,A,B,Cin,F,Cout,N);

            #5 M1=0; M0 = 1; A = 0; B = 0; Cin = 0;
            #5 A = 0; B = 0; Cin = 1;
            #5 A = 0; B = 1; Cin = 0;
            #5 A = 0; B=1; Cin=1;
            #5 A=1;B=0;Cin=0;
            #5 A=1; B=0; Cin=1;
            #5 A=1; B=1; Cin=0;
            #5 A=1; B=1; Cin=1;

            #5 $finish;
        end
        
endmodule

tb_ALU_1b.vcd
$date
	Sat Oct 14 19:27:26 2023
$end
$version
	Icarus Verilog
$end
$timescale
	1s
$end
$scope module tb_ALU_1b $end
$var wire 1 ! N $end
$var wire 1 " F $end
$var wire 1 # Cout $end
$var reg 1 $ A $end
$var reg 1 % B $end
$var reg 1 & Cin $end
$var reg 1 ' M0 $end
$var reg 1 ( M1 $end
$scope module DUT $end
$var wire 1 $ A $end
$var wire 1 % B $end
$var wire 1 & Cin $end
$var wire 1 # Cout $end
$var wire 1 " F $end
$var wire 1 ) F2 $end
$var wire 1 ' M0 $end
$var wire 1 ( M1 $end
$var wire 1 * j0 $end
$var wire 1 + j1 $end
$var wire 1 , j2 $end
$var wire 1 - t3 $end
$var wire 1 . t2 $end
$var wire 1 / t1 $end
$var wire 1 0 t0 $end
$var wire 1 ! N $end
$var wire 1 1 F1 $end
$var wire 1 2 F0 $end
$var wire 3 3 EN_sub [2:0] $end
$var wire 2 4 EN_cmp [1:0] $end
$var wire 2 5 EN_and [1:0] $end
$var wire 3 6 EN_add [2:0] $end
$var wire 1 7 C1 $end
$var wire 1 8 C0 $end
$scope module cmp1 $end
$var wire 1 9 A $end
$var wire 1 : B $end
$var wire 1 1 Eq $end
$var wire 1 7 G $end
$var wire 1 ! L $end
$upscope $end
$scope module dcd1 $end
$var wire 1 0 R0 $end
$var wire 1 / R1 $end
$var wire 1 . R2 $end
$var wire 1 - R3 $end
$var wire 1 ' S0 $end
$var wire 1 ( S1 $end
$var wire 1 ; inv0 $end
$var wire 1 < inv1 $end
$upscope $end
$scope module f1 $end
$var wire 1 * A $end
$var wire 1 + B $end
$var wire 1 , C_in $end
$var wire 1 8 C_out $end
$var wire 1 = t3 $end
$var wire 1 > t2 $end
$var wire 1 ? t1 $end
$var wire 1 2 Sum $end
$scope module H1 $end
$var wire 1 * A $end
$var wire 1 + B $end
$var wire 1 > C_out $end
$var wire 1 ? Sum $end
$upscope $end
$scope module H2 $end
$var wire 1 ? A $end
$var wire 1 , B $end
$var wire 1 = C_out $end
$var wire 1 2 Sum $end
$upscope $end
$upscope $end
$upscope $end
$upscope $end
$enddefinitions $end
#0
$dumpvars
x?
x>
x=
x<
x;
x:
x9
x8
x7
bx 6
bx 5
bx 4
bx 3
x2
x1
x0
x/
x.
x-
x,
x+
x*
x)
x(
x'
x&
x%
x$
x#
x"
x!
$end
#5
1#
0"
18
02
1=
1?
0>
1,
1+
0!
0*
11
07
0)
0:
09
00
b0 6
b110 3
b0 4
b0 5
0;
1/
1<
0.
0-
0&
0%
0$
1'
0(
#10
0#
1"
08
12
0=
0,
b10 3
1&
#15
0?
1,
0+
b100 3
0&
1%
#20
0"
02
0,
b0 3
1&
#25
1"
1#
12
18
1>
0=
1,
1+
0?
1*
b111 3
0&
0%
1$
#30
0"
02
0,
b11 3
1&
#35
1=
1?
0>
1,
0+
b101 3
0&
1%
#40
0#
1"
08
12
0=
0,
b1 3
1&
