half_adder.v
module half_adder(A,B,Sum,C_out);
    input A,B;
    output C_out,Sum;

    xor  G1  (Sum,A,B)   ;
    and G2  (C_out,A,B) ; 

endmodule

full_adder.v
`include "half_adder.v"

module full_adder(A,B,C_in,Sum,C_out);
    input   A,B,C_in    ;
    output  Sum,C_out   ;

    wire t1,t2,t3   ;

    half_adder  H1(A,B,t1,t2)       ;
    half_adder  H2(t1,C_in,Sum,t3)  ;

    xor G1(C_out,t2,t3)  ;

endmodule

tb_full_adder.v
`include "half_adder.v"
`include "full_adder.v"

module tb_full_adder;
    reg A, B, Cin;
    wire S, Cout;

    full_adder DUT(A,B,Cin,S,Cout);

    initial 
        begin
            $dumpfile("tb_full_adder.vcd");
            $dumpvars(0,tb_full_adder);

            $monitor($time," A = %b, B= %b, Cin =%b, S = %b, Cout =%b ",A,B,Cin,S,Cout);

            #10 A = 1; B = 0; Cin = 0;
            #10 A = 0; B = 0; Cin = 1;
            #10 A = 0; B = 1; Cin = 0;
            #10 A = 0; B=1; Cin=1;
            #10 A=1;B=0;Cin=0;
            #10 A=1; B=0; Cin=1;
            #10 A=1; B=1; Cin=0;
            #10 A=1; B=1; Cin=1;
            #10 $finish;
 
        end
endmodule

tb_full_adder.vcd
$date
	Fri Oct 13 20:19:56 2023
$end
$version
	Icarus Verilog
$end
$timescale
	1s
$end
$scope module tb_full_adder $end
$var wire 1 ! S $end
$var wire 1 " Cout $end
$var reg 1 # A $end
$var reg 1 $ B $end
$var reg 1 % Cin $end
$scope module DUT $end
$var wire 1 # A $end
$var wire 1 $ B $end
$var wire 1 % C_in $end
$var wire 1 " C_out $end
$var wire 1 & t3 $end
$var wire 1 ' t2 $end
$var wire 1 ( t1 $end
$var wire 1 ! Sum $end
$scope module H1 $end
$var wire 1 # A $end
$var wire 1 $ B $end
$var wire 1 ' C_out $end
$var wire 1 ( Sum $end
$upscope $end
$scope module H2 $end
$var wire 1 ( A $end
$var wire 1 % B $end
$var wire 1 & C_out $end
$var wire 1 ! Sum $end
$upscope $end
$upscope $end
$upscope $end
$enddefinitions $end
#0
$dumpvars
x(
x'
x&
x%
x$
x#
x"
x!
$end
#10
1"
0!
0&
0(
1'
0%
1$
1#
#20
1&
1(
0'
1%
0#
#30
0"
0&
0(
0%
0$
#40
1!
1%
#50
1"
0!
1'
0%
1$
1#
#60
1!
1%
#70
0"
1(
0'
0%
0$
#80
1"
0!
1&
1%
